README.md
setup.py
onepanel/__init__.py
onepanel/cli.py
onepanel/constants.py
onepanel/gitwrapper.py
onepanel/services.py
onepanel.egg-info/PKG-INFO
onepanel.egg-info/SOURCES.txt
onepanel.egg-info/dependency_links.txt
onepanel.egg-info/entry_points.txt
onepanel.egg-info/not-zip-safe
onepanel.egg-info/requires.txt
onepanel.egg-info/top_level.txt
onepanel/commands/__init__.py
onepanel/commands/base.py
onepanel/commands/common.py
onepanel/commands/datasets.py
onepanel/commands/environments.py
onepanel/commands/instances.py
onepanel/commands/jobs.py
onepanel/commands/login.py
onepanel/commands/machine_types.py
onepanel/commands/projects.py
onepanel/commands/system.py
onepanel/commands/volume_types.py
onepanel/models/__init__.py
onepanel/models/account.py
onepanel/models/api_json.py
onepanel/models/dataset_mount.py
onepanel/models/environment.py
onepanel/models/git_source.py
onepanel/models/instance.py
onepanel/models/instance_template.py
onepanel/models/job.py
onepanel/models/machine_type.py
onepanel/models/metric.py
onepanel/models/models.py
onepanel/models/project.py
onepanel/models/project_repository.py
onepanel/models/volume_type.py
onepanel/onepanel_types/__init__.py
onepanel/onepanel_types/dataset_mount_identifier.py
onepanel/onepanel_types/duration.py
onepanel/onepanel_types/git_source.py
onepanel/onepanel_types/project_repository.py
onepanel/sdk/__init__.py
onepanel/sdk/client.py
onepanel/sdk/environments.py
onepanel/sdk/jobs.py
onepanel/sdk/machine_types.py
onepanel/sdk/metrics.py
onepanel/sdk/volume_types.py
onepanel/utilities/__init__.py
onepanel/utilities/cloud_storage_utility.py
onepanel/utilities/connection.py
onepanel/utilities/creds_utility.py
onepanel/utilities/dataset_api.py
onepanel/utilities/dataset_downloader.py
onepanel/utilities/dataset_strings.py
onepanel/utilities/file.py
onepanel/utilities/gcp_utility.py
onepanel/utilities/gcs_authenticator.py
onepanel/utilities/login_helper.py
onepanel/utilities/machine_activity.py
onepanel/utilities/original_connection.py
onepanel/utilities/process.py
onepanel/utilities/python_bridge.py
onepanel/utilities/s3_authenticator.py
onepanel/utilities/time.py
onepanel/utilities/timer.py
onepanel/utilities/gcp_cs/__init__.py
