Metadata-Version: 1.2
Name: onepanel
Version: 2.20.0
Summary: Onepanel CLI
Home-page: UNKNOWN
Author: Onepanel, Inc.
Author-email: support@onepanel.io
License: UNKNOWN
Platform: UNKNOWN
Requires-Python: >=2.6, !=3.0.*, !=3.1.*, !=3.2.*, <4
